plover_spanish_system_eo_variant/__init__.py
plover_spanish_system_eo_variant/system.py
plover_spanish_system_eo_variant/dictionaries/spanish_eo_00_user.json
plover_spanish_system_eo_variant/dictionaries/spanish_eo_10_articles.json
plover_spanish_system_eo_variant/dictionaries/spanish_eo_20_main.json
plover_spanish_system_eo_variant-0.3.0.dist-info/LICENSE.txt
plover_spanish_system_eo_variant-0.3.0.dist-info/METADATA
plover_spanish_system_eo_variant-0.3.0.dist-info/WHEEL
plover_spanish_system_eo_variant-0.3.0.dist-info/entry_points.txt
plover_spanish_system_eo_variant-0.3.0.dist-info/top_level.txt
plover_spanish_system_eo_variant-0.3.0.dist-info/zip-safe
plover_spanish_system_eo_variant-0.3.0.dist-info/RECORD
